nude.py
skin_classifier.cpython-38-x86_64-linux-gnu.so
mudepy-0.5.2.dist-info/LICENSE
mudepy-0.5.2.dist-info/RECORD
mudepy-0.5.2.dist-info/top_level.txt
mudepy-0.5.2.dist-info/METADATA
mudepy-0.5.2.dist-info/entry_points.txt
mudepy-0.5.2.dist-info/WHEEL
