Metadata-Version: 2.1
Name: mudepy
Version: 0.5.2
Summary: mudepy is maintained nudepy. Nudity detection with Python. Port of nude.js to Python
Home-page: https://github.com/yaroslaff/mude.py
Author: Yaroslav Polyakov
Author-email: yaroslaff@gmail.com
License: MIT
Keywords: nude
Platform: Linux
Classifier: Development Status :: 4 - Beta
Classifier: License :: OSI Approved :: MIT License
Classifier: Operating System :: POSIX :: Linux
Classifier: Programming Language :: Python
Classifier: Programming Language :: Python :: 3
License-File: LICENSE
Requires-Dist: pillow
